[
  {
    "question": "Ricostruisci la frase (Inglese).",
    "time": 1,
    "type": "ricostruisci_frase",
    "sentence": "He is my best friend.",
    "imageUrl": ""
  },
  {
    "question": "Ricostruisci la frase (Inglese).",
    "time": 1,
    "type": "ricostruisci_frase",
    "sentence": "They are in the garden.",
    "imageUrl": ""
  },
  {
    "question": "Ricostruisci la frase (Inglese).",
    "time": 1,
    "type": "ricostruisci_frase",
    "sentence": "She is not my sister.",
    "imageUrl": ""
  },
  {
    "question": "Ricostruisci la frase (Inglese).",
    "time": 1,
    "type": "ricostruisci_frase",
    "sentence": "We are not at home.",
    "imageUrl": ""
  },
  {
    "question": "Ricostruisci la domanda (Inglese).",
    "time": 1,
    "type": "ricostruisci_frase",
    "sentence": "Is it a sunny day?",
    "imageUrl": ""
  },
  {
    "question": "Ricostruisci la domanda (Inglese).",
    "time": 1,
    "type": "ricostruisci_frase",
    "sentence": "Are you happy?",
    "imageUrl": ""
  },
  {
    "question": "Ricostruisci la frase (Inglese).",
    "time": 1,
    "type": "ricostruisci_frase",
    "sentence": "The cat is sleeping.",
    "imageUrl": ""
  },
  {
    "question": "Ricostruisci la frase (Inglese).",
    "time": 1,
    "type": "ricostruisci_frase",
    "sentence": "The dogs are playing.",
    "imageUrl": ""
  },
  {
    "question": "Ricostruisci la frase (Inglese).",
    "time": 1,
    "type": "ricostruisci_frase",
    "sentence": "My teacher isn't old.",
    "imageUrl": ""
  },
  {
    "question": "Ricostruisci la frase (Inglese).",
    "time": 1,
    "type": "ricostruisci_frase",
    "sentence": "My shoes aren't clean.",
    "imageUrl": ""
  },
  {
    "question": "Ricostruisci la domanda (Inglese).",
    "time": 1,
    "type": "ricostruisci_frase",
    "sentence": "What is your name?",
    "imageUrl": ""
  },
  {
    "question": "Ricostruisci la domanda (Inglese).",
    "time": 1,
    "type": "ricostruisci_frase",
    "sentence": "Where are my keys?",
    "imageUrl": ""
  },
  {
    "question": "Ricostruisci la frase (Inglese).",
    "time": 1,
    "type": "ricostruisci_frase",
    "sentence": "This book is interesting.",
    "imageUrl": ""
  },
  {
    "question": "Ricostruisci la frase (Inglese).",
    "time": 1,
    "type": "ricostruisci_frase",
    "sentence": "Those apples are red.",
    "imageUrl": ""
  },
  {
    "question": "Ricostruisci la frase (Inglese).",
    "time": 1,
    "type": "ricostruisci_frase",
    "sentence": "Emma and I are friends.",
    "imageUrl": ""
  },
  {
    "question": "Ricostruisci la frase (Inglese).",
    "time": 1,
    "type": "ricostruisci_frase",
    "sentence": "My brother is tall.",
    "imageUrl": ""
  },
  {
    "question": "Ricostruisci la frase (Inglese).",
    "time": 1,
    "type": "ricostruisci_frase",
    "sentence": "You and Luca are cousins.",
    "imageUrl": ""
  },
  {
    "question": "Ricostruisci la domanda (Inglese).",
    "time": 1,
    "type": "ricostruisci_frase",
    "sentence": "Is your father a doctor?",
    "imageUrl": ""
  },
  {
    "question": "Ricostruisci la domanda (Inglese).",
    "time": 1,
    "type": "ricostruisci_frase",
    "sentence": "Are your parents at home?",
    "imageUrl": ""
  },
  {
    "question": "Ricostruisci la frase (Inglese).",
    "time": 1,
    "type": "ricostruisci_frase",
    "sentence": "It isn't cold today.",
    "imageUrl": ""
  },
  {
    "question": "Ricostruisci la frase (Inglese).",
    "time": 1,
    "type": "ricostruisci_frase",
    "sentence": "We are very hungry.",
    "imageUrl": ""
  },
  {
    "question": "Ricostruisci la frase (Inglese).",
    "time": 1,
    "type": "ricostruisci_frase",
    "sentence": "The children are noisy.",
    "imageUrl": ""
  },
  {
    "question": "Ricostruisci la frase (Inglese).",
    "time": 1,
    "type": "ricostruisci_frase",
    "sentence": "That is not fair.",
    "imageUrl": ""
  },
  {
    "question": "Ricostruisci la frase (Inglese).",
    "time": 1,
    "type": "ricostruisci_frase",
    "sentence": "There is a pencil on the desk.",
    "imageUrl": ""
  },
  {
    "question": "Ricostruisci la frase (Inglese).",
    "time": 1,
    "type": "ricostruisci_frase",
    "sentence": "There are two cats outside.",
    "imageUrl": ""
  },
  {
    "question": "Ricostruisci la domanda (Inglese).",
    "time": 1,
    "type": "ricostruisci_frase",
    "sentence": "Who is she?",
    "imageUrl": ""
  },
  {
    "question": "Ricostruisci la domanda (Inglese).",
    "time": 1,
    "type": "ricostruisci_frase",
    "sentence": "How old are you?",
    "imageUrl": ""
  },
  {
    "question": "Ricostruisci la frase (Inglese).",
    "time": 1,
    "type": "ricostruisci_frase",
    "sentence": "I am tall and he is short.",
    "imageUrl": ""
  },
  {
    "question": "Ricostruisci la frase (Inglese).",
    "time": 1,
    "type": "ricostruisci_frase",
    "sentence": "The homework isn't difficult.",
    "imageUrl": ""
  },
  {
    "question": "Ricostruisci la frase (Inglese).",
    "time": 1,
    "type": "ricostruisci_frase",
    "sentence": "They are not from London.",
    "imageUrl": ""
  }
]